gptpdf/__init__.py
gptpdf/DocLayout-YOLO-standalone.py
gptpdf/doclayout_yolo.py
gptpdf/parse.py
gptpdf_latex-1.0.1.dist-info/LICENSE
gptpdf_latex-1.0.1.dist-info/METADATA
gptpdf_latex-1.0.1.dist-info/WHEEL
gptpdf_latex-1.0.1.dist-info/RECORD
