Metadata-Version: 2.3
Name: gptpdf_LaTeX
Version: 1.0.1
Summary: Using GPT to parse PDF files and generate LaTeX code.
License: Apache 2.0
Author: Federico Chiodo
Requires-Python: >=3.10,<4.0
Classifier: License :: Other/Proprietary License
Classifier: Programming Language :: Python :: 3
Classifier: Programming Language :: Python :: 3.10
Classifier: Programming Language :: Python :: 3.11
Classifier: Programming Language :: Python :: 3.12
Classifier: Programming Language :: Python :: 3.13
Requires-Dist: GeneralAgent (>=0.3.21,<0.4.0)
Requires-Dist: doclayout-yolo (>=0.0.2)
Requires-Dist: huggingface-hub (>=0.26.2,<0.27.0)
Requires-Dist: matplotlib (>=3.10.1)
Requires-Dist: numpy (>=1.26.0,<2.0.0)
Requires-Dist: pdfrw (>=0.4,<0.5)
Requires-Dist: pillow (>=11.0.0,<12.0.0)
Requires-Dist: pymupdf (>=1.24.7,<2.0.0)
Requires-Dist: python-dotenv (>=1.0.0,<2.0.0)
Requires-Dist: requests (>=2.31.0,<3.0.0)
Requires-Dist: shapely (>=2.0.7,<3.0.0)
Requires-Dist: torch (>=2.0.1)
Project-URL: Repository, https://github.com/FCPercival/gptpdf_LaTeX
